fh_fuzzy/__init__.py
fh_fuzzy/fh_funcao_pertinencia.py
fh_fuzzy/fh_operacoes.py
fh_fuzzy/fh_regras.py
fh_fuzzy/fh_variavel.py
fh_fuzzy-0.1.5.dist-info/WHEEL
fh_fuzzy-0.1.5.dist-info/METADATA
fh_fuzzy-0.1.5.dist-info/RECORD
